{
    "asset": {
        "format": "png",
        "id": "098e39958ed59f738d8658e4b88abdd0",
        "name": "0062.png",
        "path": "file:C:/Users/Ryosuke%20Nikushi/Documents/out/0062.png",
        "size": {
            "width": 1152,
            "height": 648
        },
        "state": 2,
        "type": 1
    },
    "regions": [
        {
            "id": "8sf4T1lKC",
            "type": "RECTANGLE",
            "tags": [
                "circle"
            ],
            "boundingBox": {
                "height": 315.75272727272727,
                "width": 322.7484662576687,
                "left": 80.09815950920246,
                "top": 3.6081818181818184
            },
            "points": [
                {
                    "x": 80.09815950920246,
                    "y": 3.6081818181818184
                },
                {
                    "x": 402.84662576687117,
                    "y": 3.6081818181818184
                },
                {
                    "x": 402.84662576687117,
                    "y": 319.3609090909091
                },
                {
                    "x": 80.09815950920246,
                    "y": 319.3609090909091
                }
            ]
        },
        {
            "id": "E9-ocEzEK",
            "type": "RECTANGLE",
            "tags": [
                "circle"
            ],
            "boundingBox": {
                "height": 256.8436363636364,
                "width": 266.2085889570552,
                "left": 25.914110429447856,
                "top": 364.1318181818182
            },
            "points": [
                {
                    "x": 25.914110429447856,
                    "y": 364.1318181818182
                },
                {
                    "x": 292.1226993865031,
                    "y": 364.1318181818182
                },
                {
                    "x": 292.1226993865031,
                    "y": 620.9754545454546
                },
                {
                    "x": 25.914110429447856,
                    "y": 620.9754545454546
                }
            ]
        },
        {
            "id": "yvxyzqNjW",
            "type": "RECTANGLE",
            "tags": [
                "circle"
            ],
            "boundingBox": {
                "height": 438.2836363636364,
                "width": 419.33742331288346,
                "left": 697.3251533742332,
                "top": 182.69181818181818
            },
            "points": [
                {
                    "x": 697.3251533742332,
                    "y": 182.69181818181818
                },
                {
                    "x": 1116.6625766871166,
                    "y": 182.69181818181818
                },
                {
                    "x": 1116.6625766871166,
                    "y": 620.9754545454546
                },
                {
                    "x": 697.3251533742332,
                    "y": 620.9754545454546
                }
            ]
        }
    ],
    "version": "2.2.0"
}