{
    "asset": {
        "format": "png",
        "id": "bf9d7d85934cc16e12417dd11d26676a",
        "name": "0091.png",
        "path": "file:C:/Users/Ryosuke%20Nikushi/Documents/out/0091.png",
        "size": {
            "width": 1152,
            "height": 648
        },
        "state": 2,
        "type": 1
    },
    "regions": [
        {
            "id": "rguq3l6yB",
            "type": "RECTANGLE",
            "tags": [
                "circle"
            ],
            "boundingBox": {
                "height": 233.28,
                "width": 226.159509202454,
                "left": 360.44171779141107,
                "top": 34.24090909090909
            },
            "points": [
                {
                    "x": 360.44171779141107,
                    "y": 34.24090909090909
                },
                {
                    "x": 586.6012269938651,
                    "y": 34.24090909090909
                },
                {
                    "x": 586.6012269938651,
                    "y": 267.5209090909091
                },
                {
                    "x": 360.44171779141107,
                    "y": 267.5209090909091
                }
            ]
        },
        {
            "id": "Sbob5zwit",
            "type": "RECTANGLE",
            "tags": [
                "circle"
            ],
            "boundingBox": {
                "height": 280.40727272727275,
                "width": 273.2760736196319,
                "left": 720.8834355828221,
                "top": 121.42636363636365
            },
            "points": [
                {
                    "x": 720.8834355828221,
                    "y": 121.42636363636365
                },
                {
                    "x": 994.159509202454,
                    "y": 121.42636363636365
                },
                {
                    "x": 994.159509202454,
                    "y": 401.8336363636364
                },
                {
                    "x": 720.8834355828221,
                    "y": 401.8336363636364
                }
            ]
        },
        {
            "id": "sGbelvU9h",
            "type": "RECTANGLE",
            "tags": [
                "circle"
            ],
            "boundingBox": {
                "height": 157.87636363636364,
                "width": 171.9754601226994,
                "left": 970.6012269938651,
                "top": 17.746363636363636
            },
            "points": [
                {
                    "x": 970.6012269938651,
                    "y": 17.746363636363636
                },
                {
                    "x": 1142.5766871165645,
                    "y": 17.746363636363636
                },
                {
                    "x": 1142.5766871165645,
                    "y": 175.62272727272727
                },
                {
                    "x": 970.6012269938651,
                    "y": 175.62272727272727
                }
            ]
        },
        {
            "id": "h0dRY7S3F",
            "type": "RECTANGLE",
            "tags": [
                "circle"
            ],
            "boundingBox": {
                "height": 336.96000000000004,
                "width": 336.88343558282213,
                "left": 136.63803680981596,
                "top": 288.72818181818184
            },
            "points": [
                {
                    "x": 136.63803680981596,
                    "y": 288.72818181818184
                },
                {
                    "x": 473.5214723926381,
                    "y": 288.72818181818184
                },
                {
                    "x": 473.5214723926381,
                    "y": 625.6881818181819
                },
                {
                    "x": 136.63803680981596,
                    "y": 625.6881818181819
                }
            ]
        }
    ],
    "version": "2.2.0"
}