{
    "asset": {
        "format": "png",
        "id": "f56e4aa82a5babd58570879d978a871a",
        "name": "0165.png",
        "path": "file:C:/Users/Ryosuke%20Nikushi/Documents/out/0165.png",
        "size": {
            "width": 648,
            "height": 1152
        },
        "state": 2,
        "type": 1
    },
    "regions": [
        {
            "id": "9fgen_GSU",
            "type": "RECTANGLE",
            "tags": [
                "circle"
            ],
            "boundingBox": {
                "height": 363.2313003452244,
                "width": 372.3680981595092,
                "left": 198.7730061349693,
                "top": 138.75949367088606
            },
            "points": [
                {
                    "x": 198.7730061349693,
                    "y": 138.75949367088606
                },
                {
                    "x": 571.1411042944785,
                    "y": 138.75949367088606
                },
                {
                    "x": 571.1411042944785,
                    "y": 501.99079401611044
                },
                {
                    "x": 198.7730061349693,
                    "y": 501.99079401611044
                }
            ]
        },
        {
            "id": "fLV4avhtO",
            "type": "RECTANGLE",
            "tags": [
                "circle"
            ],
            "boundingBox": {
                "height": 263.8066743383199,
                "width": 271.6564417177914,
                "left": 39.75460122699386,
                "top": 627.9286536248561
            },
            "points": [
                {
                    "x": 39.75460122699386,
                    "y": 627.9286536248561
                },
                {
                    "x": 311.41104294478527,
                    "y": 627.9286536248561
                },
                {
                    "x": 311.41104294478527,
                    "y": 891.735327963176
                },
                {
                    "x": 39.75460122699386,
                    "y": 891.735327963176
                }
            ]
        },
        {
            "id": "__tfkhrJC",
            "type": "RECTANGLE",
            "tags": [
                "circle"
            ],
            "boundingBox": {
                "height": 116.65822784810126,
                "width": 115.2883435582822,
                "left": 373.6932515337423,
                "top": 716.7479861910241
            },
            "points": [
                {
                    "x": 373.6932515337423,
                    "y": 716.7479861910241
                },
                {
                    "x": 488.9815950920245,
                    "y": 716.7479861910241
                },
                {
                    "x": 488.9815950920245,
                    "y": 833.4062140391254
                },
                {
                    "x": 373.6932515337423,
                    "y": 833.4062140391254
                }
            ]
        },
        {
            "id": "Qqh8Ig-mb",
            "type": "RECTANGLE",
            "tags": [
                "circle"
            ],
            "boundingBox": {
                "height": 241.27042577675488,
                "width": 253.10429447852758,
                "left": 381.64417177914106,
                "top": 891.735327963176
            },
            "points": [
                {
                    "x": 381.64417177914106,
                    "y": 891.735327963176
                },
                {
                    "x": 634.7484662576686,
                    "y": 891.735327963176
                },
                {
                    "x": 634.7484662576686,
                    "y": 1133.005753739931
                },
                {
                    "x": 381.64417177914106,
                    "y": 1133.005753739931
                }
            ]
        }
    ],
    "version": "2.2.0"
}