{
    "asset": {
        "format": "png",
        "id": "d324b0747e5102fb12a18268992cacca",
        "name": "0057.png",
        "path": "file:C:/Users/Ryosuke%20Nikushi/Documents/out/0057.png",
        "size": {
            "width": 1152,
            "height": 648
        },
        "state": 2,
        "type": 1
    },
    "regions": [
        {
            "id": "_O_bSgSl6",
            "type": "RECTANGLE",
            "tags": [
                "circle"
            ],
            "boundingBox": {
                "height": 174.3709090909091,
                "width": 176.68711656441718,
                "left": 537.1288343558283,
                "top": 408.9027272727273
            },
            "points": [
                {
                    "x": 537.1288343558283,
                    "y": 408.9027272727273
                },
                {
                    "x": 713.8159509202454,
                    "y": 408.9027272727273
                },
                {
                    "x": 713.8159509202454,
                    "y": 583.2736363636363
                },
                {
                    "x": 537.1288343558283,
                    "y": 583.2736363636363
                }
            ]
        }
    ],
    "version": "2.2.0"
}